unfuck/__init__.py
unfuck/foo.py
unfuck-0.0.1.dist-info/LICENSE
unfuck-0.0.1.dist-info/METADATA
unfuck-0.0.1.dist-info/WHEEL
unfuck-0.0.1.dist-info/RECORD
