Metadata-Version: 2.1
Name: unfuck
Version: 0.0.1
Summary: Use LLMs to unf*ck your codebase documentation.
Home-page: https://github.com/AlgoDistill/unfuck
Author: AlgoDistill
Author-email: 197020751+AlgoDistill@users.noreply.github.com
Requires-Python: >=3.8,<4.0
Classifier: Programming Language :: Python :: 3
Classifier: Programming Language :: Python :: 3.8
Classifier: Programming Language :: Python :: 3.9
Classifier: Programming Language :: Python :: 3.10
Classifier: Programming Language :: Python :: 3.11
Classifier: Programming Language :: Python :: 3.12
Project-URL: Documentation, https://AlgoDistill.github.io/unfuck/
Project-URL: Repository, https://github.com/AlgoDistill/unfuck
